pysmsboxnet/__init__.py
pysmsboxnet/_version.py
pysmsboxnet/api.py
pysmsboxnet/exceptions.py
pysmsboxnet/py.typed
pysmsboxnet-2024.6.1.dist-info/LICENSE
pysmsboxnet-2024.6.1.dist-info/METADATA
pysmsboxnet-2024.6.1.dist-info/WHEEL
pysmsboxnet-2024.6.1.dist-info/top_level.txt
pysmsboxnet-2024.6.1.dist-info/RECORD
